py_in_kernel-0.1.2.dist-info/licenses/LICENSE
pyinkernel/__init__.py
pyinkernel/builder.py
pyinkernel/cli.py
pyinkernel/compiler.py
pyinkernel/docgen.py
py_in_kernel-0.1.2.dist-info/METADATA
py_in_kernel-0.1.2.dist-info/WHEEL
py_in_kernel-0.1.2.dist-info/entry_points.txt
py_in_kernel-0.1.2.dist-info/top_level.txt
py_in_kernel-0.1.2.dist-info/RECORD
